vestlus/__init__.py
vestlus/api.py
vestlus/apps.py
vestlus/requires.py
vestlus/settings.py
vestlus/urls.py
vestlus/admin/__init__.py
vestlus/admin/channel.py
vestlus/admin/membership.py
vestlus/admin/message.py
vestlus/admin/actions/__init__.py
vestlus/admin/inlines/__init__.py
vestlus/admin/inlines/channel.py
vestlus/admin/inlines/membership.py
vestlus/admin/inlines/message.py
vestlus/admin/permissions/__init__.py
vestlus/fixtures/__init__.py
vestlus/forms/__init__.py
vestlus/forms/channel.py
vestlus/forms/membership.py
vestlus/forms/message.py
vestlus/forms/helpers/__init__.py
vestlus/middleware/__init__.py
vestlus/middleware/helpers/__init__.py
vestlus/migrations/0001_initial.py
vestlus/migrations/0002_auto_20200701_0012.py
vestlus/migrations/0003_channel_photo.py
vestlus/migrations/__init__.py
vestlus/models/__init__.py
vestlus/models/channel.py
vestlus/models/membership.py
vestlus/models/message.py
vestlus/models/managers/__init__.py
vestlus/models/managers/channel.py
vestlus/models/managers/membership.py
vestlus/models/managers/message.py
vestlus/models/managers/reaction.py
vestlus/models/signals/__init__.py
vestlus/models/signals/create_membership.py
vestlus/models/signals/update_index.py
vestlus/models/tests/__init__.py
vestlus/models/tests/message.py
vestlus/models/validators/__init__.py
vestlus/search_indexes/__init__.py
vestlus/search_indexes/channel.py
vestlus/search_indexes/message.py
vestlus/serializers/__init__.py
vestlus/serializers/channel.py
vestlus/serializers/membership.py
vestlus/serializers/message.py
vestlus/serializers/mixins/__init__.py
vestlus/serializers/mixins/chat.py
vestlus/serializers/mixins/exclude.py
vestlus/serializers/tests/__init__.py
vestlus/serializers/tests/channel.py
vestlus/serializers/tests/group_message.py
vestlus/serializers/tests/message.py
vestlus/templates/__init__.py
vestlus/templates/channel_create.html
vestlus/templates/channel_delete.html
vestlus/templates/channel_detail.html
vestlus/templates/channel_list.html
django_vestlus-0.1.4.dist-info/LICENSE.md
django_vestlus-0.1.4.dist-info/METADATA
django_vestlus-0.1.4.dist-info/WHEEL
django_vestlus-0.1.4.dist-info/top_level.txt
django_vestlus-0.1.4.dist-info/RECORD
