Metadata-Version: 2.1
Name: django-vestlus
Version: 0.1.4
Summary: A Django app for chat conversations
Home-page: https://www.github.com/lehvitus/vestlus
Author: Leo Neto
Author-email: leo@ekletik.com
License: BSD-3-Clause
Keywords: django chat messages
Platform: UNKNOWN
Classifier: Environment :: Web Environment
Classifier: Framework :: Django
Classifier: Framework :: Django :: 2.2
Classifier: Framework :: Django :: 3.0
Classifier: Intended Audience :: Developers
Classifier: License :: OSI Approved :: BSD License
Classifier: Operating System :: OS Independent
Classifier: Programming Language :: Python
Classifier: Programming Language :: Python :: 3 :: Only
Classifier: Programming Language :: Python :: 3.4
Classifier: Programming Language :: Python :: 3.5
Classifier: Programming Language :: Python :: 3.6
Classifier: Programming Language :: Python :: 3.7
Classifier: Programming Language :: Python :: 3.8
Classifier: Topic :: Internet :: WWW/HTTP
Classifier: Topic :: Internet :: WWW/HTTP :: Dynamic Content
Requires-Python: >= 3.4
Requires-Dist: django (>=2.2)
Requires-Dist: django-polymorphic (==2.1.2)
Requires-Dist: django-crispy-forms (>=1.9.1)
Requires-Dist: django-haystack (>=2.8.1)
Requires-Dist: djangorestframework (>=3.7.7)
